notecache/__init__.py
notecache/cache.py
notecache-0.0.1.dev1.dist-info/METADATA
notecache-0.0.1.dev1.dist-info/WHEEL
notecache-0.0.1.dev1.dist-info/licenses/LICENSE
notecache-0.0.1.dev1.dist-info/RECORD
